{"nodes":[{"block_id":"A7Lcd2THXoVcSPxIYZycJywQnee","block_type":1,"children":["XYk0dUDg5ojEB8xWWVIcNsjQnnb","V1Ogd01H6oumrlx5S3McnZ79n8g","UxTqd2D4uo0bbvx0dVmcL6tNn1b","KRJGd5PuhorgNjxZWzscUIz5ncb","Mt3zdSSvKoRgMyxdBHOchTiQnnn","IZE5dyq0poHKahxuyhfcq7DWnqf","B6LCdwmhaoUJXZxZStqcaEg2nMb","NXH0dKqQdoaeIgx9H5fc4e9bnCe","DQo8dmuRCoY6qhxjRj0cQHAbnRf","WTJXdmKQUoKk8CxRMfwcIYZrnkb","LkIAdt7wuoKD37x8L8hcSuo5nae","QwT7dRqsBo8zbfxOGqOcDrNinng","Ri1cd8TlBofPzrxGSQvcNoxanDg","Wk8PdXQgNoYlYGx6hpZcm4FcnKQ","RRuLdujmeoEeRWxSXHlcgnr8nPb","IgMFdQXIDoZuMGxC74ucofU8ntf","VJr8dse8voErR8xyVgKcGcLynqe","XUYzdbB8OoDVjFxaLdhcZeE9nVd","T2PtdEUP7oRMxLx6i1OcTQ2xnXc","MYWWdjzNRoyPTLxkGgncrzsenNc","ZFYdd5jSxo6lpoxMP8aczGsZn0g","WHdBdW5jPo5hs6xemDOc1mbNnve","UtbddhH4Xo5u9Qxi6p9cepP3nui","BHDedUVibox5nFx1hracRVofnAg","ZhIedl7MHo6kYNxFkhzcwGejnUb","C1ZZdIoIsoSy4rx5sRPc8ud9nj7","Cckydk44bojSNnxQ60fcpUUXnTd","Ttp4dwCj8oH5kkxYOO6cUfEZnSh"],"page":{"elements":[{"text_run":{"content":"第十五章 网络风险评估","text_element_style":{"bold":false,"inline_code":false,"italic":false,"strikethrough":false,"underline":false}}}],"style":{"align":1}},"parent_id":""},{"block_id":"XYk0dUDg5ojEB8xWWVIcNsjQnnb","block_type":2,"parent_id":"A7Lcd2THXoVcSPxIYZycJywQnee","text":{"elements":[{"text_run":{"content":"概念","text_element_style":{"bold":false,"inline_code":false,"italic":false,"strikethrough":false,"underline":false}}}],"style":{"align":1,"folded":false}}},{"block_id":"V1Ogd01H6oumrlx5S3McnZ79n8g","block_type":2,"parent_id":"A7Lcd2THXoVcSPxIYZycJywQnee","text":{"elements":[{"text_run":{"content":"网络风险评估就是评估威胁者利用网络资产的脆弱性，造成网络资产损失的严重程度。","text_element_style":{"bold":false,"inline_code":false,"italic":false,"strikethrough":false,"underline":false}}}],"style":{"align":1,"folded":false}}},{"block_id":"UxTqd2D4uo0bbvx0dVmcL6tNn1b","block_type":2,"parent_id":"A7Lcd2THXoVcSPxIYZycJywQnee","text":{"elements":[{"text_run":{"content":"评估模式","text_element_style":{"bold":false,"inline_code":false,"italic":false,"strikethrough":false,"underline":false}}}],"style":{"align":1,"folded":false}}},{"block_id":"KRJGd5PuhorgNjxZWzscUIz5ncb","block_type":2,"parent_id":"A7Lcd2THXoVcSPxIYZycJywQnee","text":{"elements":[{"text_run":{"content":"自评估：依靠自身力量，对自有的网络系统进行的风险评估活动。","text_element_style":{"bold":false,"inline_code":false,"italic":false,"strikethrough":false,"underline":false}}}],"style":{"align":1,"folded":false}}},{"block_id":"Mt3zdSSvKoRgMyxdBHOchTiQnnn","block_type":2,"parent_id":"A7Lcd2THXoVcSPxIYZycJywQnee","text":{"elements":[{"text_run":{"content":"检查评估：由网络安全主管机关或业务主管机关发起，旨在依据已经颁布的安全法规、安 全标准或安全管理规定等进行检查评估。","text_element_style":{"bold":false,"inline_code":false,"italic":false,"strikethrough":false,"underline":false}}}],"style":{"align":1,"folded":false}}},{"block_id":"IZE5dyq0poHKahxuyhfcq7DWnqf","block_type":2,"parent_id":"A7Lcd2THXoVcSPxIYZycJywQnee","text":{"elements":[{"text_run":{"content":"委托评估：网络系统使用单位委托具有风险评估能力的专业评估机构实施的评估活动。","text_element_style":{"bold":false,"inline_code":false,"italic":false,"strikethrough":false,"underline":false}}}],"style":{"align":1,"folded":false}}},{"block_id":"B6LCdwmhaoUJXZxZStqcaEg2nMb","block_type":2,"parent_id":"A7Lcd2THXoVcSPxIYZycJywQnee","text":{"elements":[{"text_run":{"content":"评估过程","text_element_style":{"bold":false,"inline_code":false,"italic":false,"strikethrough":false,"underline":false}}}],"style":{"align":1,"folded":false}}},{"block_id":"NXH0dKqQdoaeIgx9H5fc4e9bnCe","block_type":27,"image":{"align":2,"height":610,"token":"JHqtbJeyjo98rAxDgoscxmoXnGh","width":702},"parent_id":"A7Lcd2THXoVcSPxIYZycJywQnee"},{"block_id":"DQo8dmuRCoY6qhxjRj0cQHAbnRf","block_type":2,"parent_id":"A7Lcd2THXoVcSPxIYZycJywQnee","text":{"elements":[{"text_run":{"content":"网络安全风险计算方法","text_element_style":{"bold":false,"inline_code":false,"italic":false,"strikethrough":false,"underline":false}}}],"style":{"align":1,"folded":false}}},{"block_id":"WTJXdmKQUoKk8CxRMfwcIYZrnkb","block_type":13,"ordered":{"elements":[{"text_run":{"content":"相乘法","text_element_style":{"bold":false,"inline_code":false,"italic":false,"strikethrough":false,"underline":false}}}],"style":{"align":1,"folded":false,"sequence":"1"}},"parent_id":"A7Lcd2THXoVcSPxIYZycJywQnee"},{"block_id":"LkIAdt7wuoKD37x8L8hcSuo5nae","block_type":2,"parent_id":"A7Lcd2THXoVcSPxIYZycJywQnee","text":{"elements":[{"text_run":{"content":"是将安全事件发生的可能性与安全事件的损失进行相乘运算得到风险值","text_element_style":{"bold":false,"inline_code":false,"italic":false,"strikethrough":false,"underline":false}}}],"style":{"align":1,"folded":false,"indentation_level":"OneLevelIndent"}}},{"block_id":"QwT7dRqsBo8zbfxOGqOcDrNinng","block_type":2,"parent_id":"A7Lcd2THXoVcSPxIYZycJywQnee","text":{"elements":[{"equation":{"content":" z=f(x,y)=\\sqrt{xy}\n\n","text_element_style":{"bold":false,"inline_code":false,"italic":false,"strikethrough":false,"underline":false}}}],"style":{"align":1,"folded":false,"indentation_level":"OneLevelIndent"}}},{"block_id":"Ri1cd8TlBofPzrxGSQvcNoxanDg","block_type":13,"ordered":{"elements":[{"text_run":{"content":"矩阵法","text_element_style":{"bold":false,"inline_code":false,"italic":false,"strikethrough":false,"underline":false}}}],"style":{"align":1,"folded":false,"sequence":"auto"}},"parent_id":"A7Lcd2THXoVcSPxIYZycJywQnee"},{"block_id":"Wk8PdXQgNoYlYGx6hpZcm4FcnKQ","block_type":2,"parent_id":"A7Lcd2THXoVcSPxIYZycJywQnee","text":{"elements":[{"text_run":{"content":"指通过构造一个二维矩阵，形成安全事件发生的可能性与安全事件的损失之间 的二维关系","text_element_style":{"bold":false,"inline_code":false,"italic":false,"strikethrough":false,"underline":false}}}],"style":{"align":1,"folded":false,"indentation_level":"OneLevelIndent"}}},{"block_id":"RRuLdujmeoEeRWxSXHlcgnr8nPb","block_type":2,"parent_id":"A7Lcd2THXoVcSPxIYZycJywQnee","text":{"elements":[{"text_run":{"content":"网络安全渗透测试","text_element_style":{"bold":false,"inline_code":false,"italic":false,"strikethrough":false,"underline":false}}}],"style":{"align":1,"folded":false}}},{"block_id":"IgMFdQXIDoZuMGxC74ucofU8ntf","block_type":2,"parent_id":"A7Lcd2THXoVcSPxIYZycJywQnee","text":{"elements":[{"text_run":{"content":"主要工作：目标系统的安全漏洞发现、网络攻击路径构造、安全漏洞利用验证等。","text_element_style":{"bold":false,"inline_code":false,"italic":false,"strikethrough":false,"underline":false}}}],"style":{"align":1,"folded":false}}},{"block_id":"VJr8dse8voErR8xyVgKcGcLynqe","block_type":12,"bullet":{"elements":[{"text_run":{"content":"常见的渗透测试集成工具箱有BackTrack5、 Metasploit、 Cobalt Strike等。","text_element_style":{"bold":false,"inline_code":false,"italic":false,"strikethrough":false,"underline":false}}}],"style":{"align":1,"folded":false}},"parent_id":"A7Lcd2THXoVcSPxIYZycJywQnee"},{"block_id":"XUYzdbB8OoDVjFxaLdhcZeE9nVd","block_type":2,"parent_id":"A7Lcd2THXoVcSPxIYZycJywQnee","text":{"elements":[{"text_run":{"content":"Cobalt Strike 是一个商业 化渗透平台，提供网络敌手仿真和渗透操作","text_element_style":{"bold":false,"inline_code":false,"italic":false,"strikethrough":false,"underline":false}}}],"style":{"align":1,"folded":false,"indentation_level":"OneLevelIndent"}}},{"block_id":"T2PtdEUP7oRMxLx6i1OcTQ2xnXc","block_type":12,"bullet":{"elements":[{"text_run":{"content":"口令破解工具有 John the Ripper、朔雪、 brutus-aet2、 Cain and Abel 等","text_element_style":{"bold":false,"inline_code":false,"italic":false,"strikethrough":false,"underline":false}}}],"style":{"align":1,"folded":false}},"parent_id":"A7Lcd2THXoVcSPxIYZycJywQnee"},{"block_id":"MYWWdjzNRoyPTLxkGgncrzsenNc","block_type":12,"bullet":{"elements":[{"text_run":{"content":"Web 应用系统安全分析工具，如 Webscarab、 AppScan 等。","text_element_style":{"bold":false,"inline_code":false,"italic":false,"strikethrough":false,"underline":false}}}],"style":{"align":1,"folded":false}},"parent_id":"A7Lcd2THXoVcSPxIYZycJywQnee"},{"block_id":"ZFYdd5jSxo6lpoxMP8aczGsZn0g","block_type":2,"parent_id":"A7Lcd2THXoVcSPxIYZycJywQnee","text":{"elements":[{"text_run":{"content":"入侵监测的工具和系统如下：","text_element_style":{"bold":false,"inline_code":false,"italic":false,"strikethrough":false,"underline":false}}}],"style":{"align":1,"folded":false}}},{"block_id":"WHdBdW5jPo5hs6xemDOc1mbNnve","block_type":12,"bullet":{"elements":[{"text_run":{"content":"网络协议分析器，如Tcpdump、Wireshark;","text_element_style":{"bold":false,"inline_code":false,"italic":false,"strikethrough":false,"underline":false}}}],"style":{"align":1,"folded":false}},"parent_id":"A7Lcd2THXoVcSPxIYZycJywQnee"},{"block_id":"UtbddhH4Xo5u9Qxi6p9cepP3nui","block_type":12,"bullet":{"elements":[{"text_run":{"content":"入侵检测系统：开源入侵检测系统Snort、 Suricata、 Bro ","text_element_style":{"bold":false,"inline_code":false,"italic":false,"strikethrough":false,"underline":false}}}],"style":{"align":1,"folded":false}},"parent_id":"A7Lcd2THXoVcSPxIYZycJywQnee"},{"block_id":"BHDedUVibox5nFx1hracRVofnAg","block_type":12,"bullet":{"elements":[{"text_run":{"content":" Windows 系统注册表监测，如 regedit;  ","text_element_style":{"bold":false,"inline_code":false,"italic":false,"strikethrough":false,"underline":false}}}],"style":{"align":1,"folded":false}},"parent_id":"A7Lcd2THXoVcSPxIYZycJywQnee"},{"block_id":"ZhIedl7MHo6kYNxFkhzcwGejnUb","block_type":12,"bullet":{"elements":[{"text_run":{"content":"Windows 系统安全状态分析，如 ProcessExplorer、 Autoruns、 Process Monitor 等","text_element_style":{"bold":false,"inline_code":false,"italic":false,"strikethrough":false,"underline":false}}}],"style":{"align":1,"folded":false}},"parent_id":"A7Lcd2THXoVcSPxIYZycJywQnee"},{"block_id":"C1ZZdIoIsoSy4rx5sRPc8ud9nj7","block_type":12,"bullet":{"elements":[{"text_run":{"content":"恶意代码检测：如RootkitRevealer、 ClamAV; ","text_element_style":{"bold":false,"inline_code":false,"italic":false,"strikethrough":false,"underline":false}}}],"style":{"align":1,"folded":false}},"parent_id":"A7Lcd2THXoVcSPxIYZycJywQnee"},{"block_id":"Cckydk44bojSNnxQ60fcpUUXnTd","block_type":12,"bullet":{"elements":[{"text_run":{"content":"文件完整性检查：如Tripwire、 MD5sum。","text_element_style":{"bold":false,"inline_code":false,"italic":false,"strikethrough":false,"underline":false}}}],"style":{"align":1,"folded":false}},"parent_id":"A7Lcd2THXoVcSPxIYZycJywQnee"},{"block_id":"Ttp4dwCj8oH5kkxYOO6cUfEZnSh","block_type":2,"parent_id":"A7Lcd2THXoVcSPxIYZycJywQnee","text":{"elements":[{"text_run":{"content":"","text_element_style":{"bold":false,"inline_code":false,"italic":false,"strikethrough":false,"underline":false}}}],"style":{"align":1,"folded":false}}}],"type":"docx"}